pyvhd/__init__.py
pyvhd-0.0.1.dist-info/LICENSE
pyvhd-0.0.1.dist-info/METADATA
pyvhd-0.0.1.dist-info/WHEEL
pyvhd-0.0.1.dist-info/top_level.txt
pyvhd-0.0.1.dist-info/RECORD
