Metadata-Version: 2.1
Name: pyvhd
Version: 0.0.1
Summary: Pure python code to create dynamic VHD files for Xen/Xenserver imports
Home-page: https://github.com/lungj/pyvhd
Author: Ian McLeod
Author-email: imcleod@redhat.com
License: UNKNOWN
Platform: UNKNOWN
Classifier: Programming Language :: Python :: 3
Classifier: License :: OSI Approved :: GNU Lesser General Public License v2 or later (LGPLv2+)
Classifier: Operating System :: OS Independent
Requires-Python: >=3.2
